justin_furuness/__init__.py
justin_furuness/__main__.py
justin_furuness/names.txt
justin_furuness/speaker.py
justin_furuness/speakers/__init__.py
justin_furuness/speakers/justin.py
justin_furuness-0.3.0.dist-info/LICENSE.txt
justin_furuness-0.3.0.dist-info/METADATA
justin_furuness-0.3.0.dist-info/WHEEL
justin_furuness-0.3.0.dist-info/entry_points.txt
justin_furuness-0.3.0.dist-info/top_level.txt
justin_furuness-0.3.0.dist-info/RECORD
