Metadata-Version: 2.2
Name: justin_furuness
Version: 0.3.0
Summary: My first package!
Author-email: Justin Furuness <jfuruness@gmail.com>
Maintainer-email: Justin Furuness <jfuruness@gmail.com>
License: Copyright 2025 Justin Furuness
Project-URL: Homepage, https://github.com/jfuruness/justin_furuness
Project-URL: Documentation, https://github.com/jfuruness/justin_furuness/README.md
Keywords: Furuness
Classifier: Programming Language :: Python :: 3.9
Classifier: Programming Language :: Python :: Implementation :: CPython
Classifier: License :: OSI Approved :: BSD License
Classifier: Intended Audience :: Developers
Classifier: Operating System :: POSIX :: Linux
Classifier: Operating System :: Microsoft :: Windows
Classifier: Operating System :: MacOS
Classifier: Operating System :: MacOS :: MacOS X
Requires-Python: >=3.9
License-File: LICENSE.txt
Requires-Dist: colorama~=0.0
Provides-Extra: dev
Requires-Dist: twine; extra == "dev"
Requires-Dist: build; extra == "dev"
